trolo/__init__.py
trolo/infer.py
trolo/train.py
trolo/visualize.py
trolo/cli/__init__.py
trolo/cli/cli.py
trolo/configs/yaml/runtime.yml
trolo/configs/yaml/dataset/coco_detection.yml
trolo/configs/yaml/dataset/crowdhuman_detection.yml
trolo/configs/yaml/dataset/custom_detection.yml
trolo/configs/yaml/dataset/dummy_coco.yml
trolo/configs/yaml/dataset/obj365_detection.yml
trolo/configs/yaml/dataset/voc_detection.yml
trolo/configs/yaml/dfine/dfine_hgnetv2_n_coco_half.yml
trolo/configs/yaml/dfine/dfine_l.yml
trolo/configs/yaml/dfine/dfine_m.yml
trolo/configs/yaml/dfine/dfine_n.yml
trolo/configs/yaml/dfine/dfine_n_coco_dummy.yml
trolo/configs/yaml/dfine/dfine_s.yml
trolo/configs/yaml/dfine/dfine_x.yml
trolo/configs/yaml/dfine/n_exp.yml
trolo/configs/yaml/dfine/crowdhuman/dfine_hgnetv2_l_ch.yml
trolo/configs/yaml/dfine/crowdhuman/dfine_hgnetv2_m_ch.yml
trolo/configs/yaml/dfine/crowdhuman/dfine_hgnetv2_n_ch.yml
trolo/configs/yaml/dfine/crowdhuman/dfine_hgnetv2_s_ch.yml
trolo/configs/yaml/dfine/crowdhuman/dfine_hgnetv2_x_ch.yml
trolo/configs/yaml/dfine/custom/dfine_hgnetv2_l_custom.yml
trolo/configs/yaml/dfine/custom/dfine_hgnetv2_m_custom.yml
trolo/configs/yaml/dfine/custom/dfine_hgnetv2_n_custom.yml
trolo/configs/yaml/dfine/custom/dfine_hgnetv2_s_custom.yml
trolo/configs/yaml/dfine/custom/dfine_hgnetv2_x_custom.yml
trolo/configs/yaml/dfine/custom/objects365/dfine_hgnetv2_l_obj2custom.yml
trolo/configs/yaml/dfine/custom/objects365/dfine_hgnetv2_m_obj2custom.yml
trolo/configs/yaml/dfine/custom/objects365/dfine_hgnetv2_s_obj2custom.yml
trolo/configs/yaml/dfine/custom/objects365/dfine_hgnetv2_x_obj2custom.yml
trolo/configs/yaml/dfine/include/back_exp.yml
trolo/configs/yaml/dfine/include/dataloader.yml
trolo/configs/yaml/dfine/include/dfine_hgnetv2.yml
trolo/configs/yaml/dfine/include/optimizer.yml
trolo/configs/yaml/dfine/objects365/dfine_hgnetv2_l_obj2coco.yml
trolo/configs/yaml/dfine/objects365/dfine_hgnetv2_l_obj365.yml
trolo-0.1.31.dist-info/METADATA
trolo-0.1.31.dist-info/WHEEL
trolo-0.1.31.dist-info/entry_points.txt
trolo-0.1.31.dist-info/top_level.txt
trolo-0.1.31.dist-info/RECORD
